commanderbot_lib/__init__.py
commanderbot_lib/bot/__init__.py
commanderbot_lib/bot/abc/__init__.py
commanderbot_lib/bot/abc/commander_bot_base.py
commanderbot_lib/bot/commander_bot.py
commanderbot_lib/checks.py
commanderbot_lib/database/__init__.py
commanderbot_lib/database/abc/cog_database.py
commanderbot_lib/database/abc/dict_database.py
commanderbot_lib/database/abc/file_database.py
commanderbot_lib/database/abc/read_only_remote_file_database.py
commanderbot_lib/database/abc/versioned_file_database.py
commanderbot_lib/database/in_memory_dict_database.py
commanderbot_lib/database/json_file_database.py
commanderbot_lib/database/json_read_only_remote_file_database.py
commanderbot_lib/database/json_versioned_file_database.py
commanderbot_lib/database/mixins/__init__.py
commanderbot_lib/database/mixins/json_file_database_mixin.py
commanderbot_lib/database/mixins/yaml_file_database_mixin.py
commanderbot_lib/database/yaml_file_database.py
commanderbot_lib/database/yaml_read_only_remote_file_database.py
commanderbot_lib/database/yaml_versioned_file_database.py
commanderbot_lib/guild_state/__init__.py
commanderbot_lib/guild_state/abc/__init__.py
commanderbot_lib/guild_state/abc/cog_guild_state.py
commanderbot_lib/logging.py
commanderbot_lib/mixins/__init__.py
commanderbot_lib/mixins/async_init_mixin.py
commanderbot_lib/options/__init__.py
commanderbot_lib/options/abc/__init__.py
commanderbot_lib/options/abc/cog_options.py
commanderbot_lib/options/abc/options_with_database.py
commanderbot_lib/state/__init__.py
commanderbot_lib/state/abc/__init__.py
commanderbot_lib/state/abc/cog_state.py
commanderbot_lib/store/__init__.py
commanderbot_lib/store/abc/__init__.py
commanderbot_lib/store/abc/cached_store.py
commanderbot_lib/store/abc/cog_store.py
commanderbot_lib/store/abc/versioned_cached_store.py
commanderbot_lib/store/simple_dict_store.py
commanderbot_lib/types.py
commanderbot_lib/utils.py
commanderbot_lib-0.6.0.dist-info/LICENSE.txt
commanderbot_lib-0.6.0.dist-info/WHEEL
commanderbot_lib-0.6.0.dist-info/METADATA
commanderbot_lib-0.6.0.dist-info/RECORD
